{
  "PlanningHorizon": 30,
  "PastHorizon": 3,
  "PeakHorizon": 5,
  "StationDeclarations": [
    {
      "StationIndex": 0,
      "ProcessingTime": 0.01,
      "LeadTime": 2,
      "InitialBuffer": 20,
      "PastBuffer": [ 0, 0, 0 ],
      "PastOrderAmount": [ 0, 0, 0 ],
      "NextStationsInput": [
        {
          "NextStationIndex": 1,
          "InputAmount": 1
        },
        {
          "NextStationIndex": 2,
          "InputAmount": 1
        }
      ]
    },
    {
      "StationIndex": 1,
      "ProcessingTime": 0.02,
      "PastBuffer": [ 0, 0, 0 ],
      "PastOrderAmount": [ 0, 0, 0 ],
      "NextStationsInput": [
        {
          "NextStationIndex": 3,
          "InputAmount": 1
        }
      ]
    },
    {
      "StationIndex": 2,
      "ProcessingTime": 0.02,
      "PastBuffer": [ 0, 0, 0 ],
      "PastOrderAmount": [ 0, 0, 0 ],
      "NextStationsInput": [
        {
          "NextStationIndex": 4,
          "InputAmount": 1
        }
      ]
    },
    {
      "StationIndex": 3,
      "ProcessingTime": 0.02,
      "PastBuffer": [ 0, 0, 0 ],
      "PastOrderAmount": [ 0, 0, 0 ],
      "NextStationsInput": [
        {
          "NextStationIndex": 5,
          "InputAmount": 1
        }
      ]
    },
    {
      "StationIndex": 4,
      "ProcessingTime": 0.02,
      "PastBuffer": [ 0, 0, 0 ],
      "PastOrderAmount": [ 0, 0, 0 ],
      "NextStationsInput": [
        {
          "NextStationIndex": 6,
          "InputAmount": 1
        }
      ]
    },
    {
      "StationIndex": 5,
      "ProcessingTime": 0.02,
      "PastBuffer": [ 0, 0, 0 ],
      "PastOrderAmount": [ 0, 0, 0 ],
      "NextStationsInput": [
        {
          "NextStationIndex": 7,
          "InputAmount": 1
        }
      ]
    },
    {
      "StationIndex": 6,
      "ProcessingTime": 0.02,
      "PastBuffer": [ 0, 0, 0 ],
      "PastOrderAmount": [ 0, 0, 0 ],
      "NextStationsInput": [
        {
          "NextStationIndex": 8,
          "InputAmount": 1
        }
      ]
    },
    {
      "StationIndex": 7,
      "ProcessingTime": 0.02,
      "PastBuffer": [ 0, 0, 0 ],
      "PastOrderAmount": [ 0, 0, 0 ],
      "NextStationsInput": [
        {
          "NextStationIndex": 9,
          "InputAmount": 1
        }
      ]
    },
    {
      "StationIndex": 8,
      "ProcessingTime": 0.02,
      "PastBuffer": [ 0, 0, 0 ],
      "PastOrderAmount": [ 0, 0, 0 ],
      "NextStationsInput": [
        {
          "NextStationIndex": 10,
          "InputAmount": 1
        }
      ]
    },
    {
      "StationIndex": 9,
      "ProcessingTime": 0.02,
      "DemandVariability": 17,
      "DemandForecast": [
        40,
        15,
        25,
        60,
        75,
        35,
        53,
        22,
        30,
        60,
        65,
        40,
        25,
        35,
        53,
        65,
        50,
        40,
        25,
        40,
        22,
        35,
        53,
        65,
        50,
        53,
        22,
        16,
        53,
        22
      ],
      "PastBuffer": [ 15, 15, 15 ],
      "PastOrderAmount": [ 10, 10, 10 ]
    },
    {
      "StationIndex": 10,
      "ProcessingTime": 0.02,
      "DemandVariability": 17,
      "DemandForecast": [
        40,
        15,
        25,
        60,
        75,
        35,
        53,
        22,
        30,
        60,
        65,
        40,
        25,
        35,
        53,
        65,
        50,
        40,
        25,
        40,
        22,
        35,
        53,
        65,
        50,
        53,
        22,
        16,
        53,
        22
      ],
      "PastBuffer": [ 15, 15, 15 ],
      "PastOrderAmount": [ 10, 10, 10 ]
    }
  ]
}